cli/__init__.py
cli/cli.py
commands/__init__.py
commands/scrape.py
commands/split.py
lib/__init__.py
lib/jsonio.py
wayble-1.1.3.dist-info/LICENSE
wayble-1.1.3.dist-info/METADATA
wayble-1.1.3.dist-info/WHEEL
wayble-1.1.3.dist-info/entry_points.txt
wayble-1.1.3.dist-info/top_level.txt
wayble-1.1.3.dist-info/RECORD
